travail/__init__.py
travail/analyze.py
travail/main.py
travail/methods.py
travail/preprocess.py
travail/test.py
travail/utils.py
travail-0.0.1.dev0.dist-info/LICENSE
travail-0.0.1.dev0.dist-info/METADATA
travail-0.0.1.dev0.dist-info/WHEEL
travail-0.0.1.dev0.dist-info/entry_points.txt
travail-0.0.1.dev0.dist-info/top_level.txt
travail-0.0.1.dev0.dist-info/RECORD
