Metadata-Version: 2.1
Name: travail
Version: 0.0.1.dev0
Summary: Pipeline for processing samples in context of rare mendelian diseases
Home-page: https://github.com/ielis/travail
Author: Daniel Danis
Author-email: daniel.gordon.danis@gmail.com
License: GPLv3
Keywords: bioinformatics genomics mendelian disease exome genome sequencing
Platform: UNKNOWN
Requires-Dist: toil (>=3.20.0)
Requires-Dist: requests (>=2.22.0)
Requires-Dist: protobuf (>=3.8.0)
Requires-Dist: pyyaml (>=5.1.2)
